{
  "symbol": "MSFT",
  "source": "trend_analysis",
  "daily_trends": [
    {
      "date": "2025-06-09",
      "sentiment_score": 0.17233033975381123,
      "news_volume": 49,
      "social_mentions": 32
    },
    {
      "date": "2025-06-08",
      "sentiment_score": 0.13156779179924652,
      "news_volume": 15,
      "social_mentions": 191
    },
    {
      "date": "2025-06-07",
      "sentiment_score": -0.6303484664489817,
      "news_volume": 7,
      "social_mentions": 18
    },
    {
      "date": "2025-06-06",
      "sentiment_score": 0.14689558264344799,
      "news_volume": 13,
      "social_mentions": 141
    },
    {
      "date": "2025-06-05",
      "sentiment_score": 0.38521095334359423,
      "news_volume": 22,
      "social_mentions": 114
    },
    {
      "date": "2025-06-04",
      "sentiment_score": -0.015605679176538934,
      "news_volume": 12,
      "social_mentions": 23
    },
    {
      "date": "2025-06-03",
      "sentiment_score": -0.30131357939048176,
      "news_volume": 39,
      "social_mentions": 191
    },
    {
      "date": "2025-06-02",
      "sentiment_score": 0.11263791640522469,
      "news_volume": 37,
      "social_mentions": 116
    },
    {
      "date": "2025-06-01",
      "sentiment_score": -0.5762236510519971,
      "news_volume": 38,
      "social_mentions": 158
    },
    {
      "date": "2025-05-31",
      "sentiment_score": 0.17411909560122596,
      "news_volume": 9,
      "social_mentions": 177
    },
    {
      "date": "2025-05-30",
      "sentiment_score": 0.22029449687814961,
      "news_volume": 20,
      "social_mentions": 184
    },
    {
      "date": "2025-05-29",
      "sentiment_score": 0.5731085409971653,
      "news_volume": 35,
      "social_mentions": 45
    },
    {
      "date": "2025-05-28",
      "sentiment_score": -0.23628875335465566,
      "news_volume": 39,
      "social_mentions": 179
    },
    {
      "date": "2025-05-27",
      "sentiment_score": -0.397641050883169,
      "news_volume": 24,
      "social_mentions": 177
    },
    {
      "date": "2025-05-26",
      "sentiment_score": -0.16545783875879289,
      "news_volume": 28,
      "social_mentions": 121
    },
    {
      "date": "2025-05-25",
      "sentiment_score": 0.08475733317210318,
      "news_volume": 16,
      "social_mentions": 127
    },
    {
      "date": "2025-05-24",
      "sentiment_score": 0.1990547691500066,
      "news_volume": 47,
      "social_mentions": 174
    },
    {
      "date": "2025-05-23",
      "sentiment_score": -0.08482638085304517,
      "news_volume": 11,
      "social_mentions": 24
    },
    {
      "date": "2025-05-22",
      "sentiment_score": -0.4589908371482892,
      "news_volume": 9,
      "social_mentions": 49
    },
    {
      "date": "2025-05-21",
      "sentiment_score": 0.3876959316695575,
      "news_volume": 46,
      "social_mentions": 151
    },
    {
      "date": "2025-05-20",
      "sentiment_score": -0.35473343031866955,
      "news_volume": 22,
      "social_mentions": 109
    },
    {
      "date": "2025-05-19",
      "sentiment_score": -0.08139136388809529,
      "news_volume": 23,
      "social_mentions": 158
    },
    {
      "date": "2025-05-18",
      "sentiment_score": -0.11189616786460485,
      "news_volume": 11,
      "social_mentions": 179
    },
    {
      "date": "2025-05-17",
      "sentiment_score": 0.1382600578235625,
      "news_volume": 38,
      "social_mentions": 23
    },
    {
      "date": "2025-05-16",
      "sentiment_score": -0.2635491376112629,
      "news_volume": 13,
      "social_mentions": 52
    },
    {
      "date": "2025-05-15",
      "sentiment_score": 0.2614904102907817,
      "news_volume": 31,
      "social_mentions": 112
    },
    {
      "date": "2025-05-14",
      "sentiment_score": 0.016549013309350047,
      "news_volume": 7,
      "social_mentions": 16
    },
    {
      "date": "2025-05-13",
      "sentiment_score": -0.02086489894241622,
      "news_volume": 47,
      "social_mentions": 32
    },
    {
      "date": "2025-05-12",
      "sentiment_score": -0.38055221430191943,
      "news_volume": 33,
      "social_mentions": 44
    },
    {
      "date": "2025-05-11",
      "sentiment_score": 0.35490887827829326,
      "news_volume": 12,
      "social_mentions": 144
    }
  ],
  "moving_averages": {
    "ma_7": [
      -0.015894722496557476,
      -0.024422211546355554,
      -0.12553527481081894,
      -0.010611337375074976,
      -0.00012577819868904438,
      0.026716734323249704,
      -0.00480941913076699,
      -0.01857048648686515,
      -0.05829845151029624,
      0.03612740337886094,
      0.03968964245725818,
      -0.003899054361483932,
      -0.1513418226679774,
      -0.06220115337880411,
      -0.05607149329816135,
      -0.044061996888061686,
      -0.07215535417901997,
      -0.08084031293994054,
      -0.10637213533397168,
      -0.003446242842675841,
      -0.05646723117984833,
      -0.008771726697526435,
      -0.051508991042358454,
      0.015177444120912702
    ],
    "ma_14": [
      -0.017232604491711313,
      -0.04136033152832589,
      -0.044703935715978985,
      0.014539152541091595,
      -0.0020124162800864986,
      -0.06231254417236387,
      -0.03350528625478556,
      -0.037320989892513264,
      -0.051180224199178975,
      -0.018013975400079534,
      -0.020575335241341204,
      -0.055135594847727815,
      -0.07739403275532664,
      -0.05933419227932624,
      -0.032421609997843895,
      -0.04778549396521007,
      -0.02848895502905363
    ]
  },
  "current_trend": "Stable",
  "volatility": 0.29831644173612265,
  "avg_sentiment": -0.024026744629246647,
  "timestamp": "2025-06-09T12:44:29.433431"
}